Pacemaker (Verilog)/pacemaker_fsm.v
// pacemaker_fsm.v
`timescale 1ns/1ps

module pacemaker_fsm (
    input  wire clk,
    input  wire rst,
    // Input Sensor (1 = Normal, 0 = Abnormal)
    input  wire VT,    // Volume Tidal
    input  wire RR,    // Respiratory Rate
    input  wire FiO2,  // Fraksi Oksigen
    input  wire PEEP,  // Tekanan Positif
    input  wire EP,    // Effort Pasien
    input  wire SpO2,  // Saturasi Oksigen
    
    // Output Actuator & Alarm sesuai Tabel
    output reg  PS,    // Pressure Support
    output reg  PV,    // PEEP Valve
    output reg  FM,    // Flow Mixer
    output reg  MS,    // Machine Support
    output reg  AL,    // Alarm
    output reg  SBT,   // Spontaneous Breathing Trial
    output reg [2:0] state // Debug State
);

    // --- 1. STATE ENCODING (Sesuai Tabel FSM) ---
    localparam STANDBY     = 3'b000;
    localparam MONITOR     = 3'b001; // All OK
    localparam ASSIST      = 3'b010; // Pasien Lemah
    localparam SUPPORT     = 3'b011; // Mode Mesin (VT Fail)
    localparam ADJ_PEEP    = 3'b100; // PEEP Correction
    localparam ADJ_FIO2    = 3'b101; // O2 Correction
    localparam WEAN        = 3'b110; // Weaning Mode
    localparam EMERGENCY   = 3'b111; // Critical / Multi Fail

    reg [2:0] curr_state, next_state;

    // --- 2. LOGIKA TRANSISI (Next State Logic) ---
    // Variabel bantu untuk menghitung jumlah kegagalan sensor
    wire [2:0] fail_count;
    wire all_ok;
    
    // Menghitung berapa sensor yang bernilai 0 (Abnormal)
    assign fail_count = (!VT) + (!RR) + (!FiO2) + (!PEEP) + (!EP) + (!SpO2);
    assign all_ok = (fail_count == 0);

    always @(*) begin
        next_state = curr_state; // Default hold

        case (curr_state)
            // State: STANDBY
            STANDBY: begin
                if (all_ok) next_state = MONITOR;
                else if (fail_count >= 3) next_state = EMERGENCY;
            end

            // State Operational (MONITOR, ASSIST, etc)
            MONITOR, ASSIST, SUPPORT, ADJ_PEEP, ADJ_FIO2, WEAN: begin
                // PRIORITAS 1: Emergency (Jika banyak sensor gagal sekaligus)
                // Lihat tabel: "Banyak sensor gagal -> Emergency"
                if (fail_count >= 3) begin
                    next_state = EMERGENCY;
                end
                // PRIORITAS 2: Normal (Recovery)
                else if (all_ok) begin
                    next_state = MONITOR;
                end
                // PRIORITAS 3: Machine Support (VT rendah sangat fatal)
                // Tabel: VT rendah -> ModeSelect (MS) aktif -> State SUPPORT
                else if (VT == 0) begin
                    next_state = SUPPORT;
                end
                // PRIORITAS 4: Masalah Oksigen (FiO2 atau SpO2)
                // Tabel: O2/FiO2 rendah -> Mixer (FM) aktif -> State ADJ_FIO2
                else if (FiO2 == 0 || SpO2 == 0) begin
                    next_state = ADJ_FIO2;
                end
                // PRIORITAS 5: Masalah PEEP
                // Tabel: PEEP rendah -> Valve (PV) aktif -> State ADJ_PEEP
                else if (PEEP == 0) begin
                    next_state = ADJ_PEEP;
                end
                // PRIORITAS 6: Masalah Napas Ringan (RR atau EP)
                // Tabel: RR/EP rendah -> PS aktif -> State ASSIST
                else if (RR == 0 || EP == 0) begin
                    next_state = ASSIST;
                end
            end

            // State: EMERGENCY
            EMERGENCY: begin
                if (all_ok) next_state = MONITOR; // Pulih total
                else next_state = EMERGENCY;      // Tetap alarm
            end
        endcase
    end

    // --- 3. STATE REGISTER (Sequential) ---
    always @(posedge clk or posedge rst) begin
        if (rst) curr_state <= STANDBY;
        else curr_state <= next_state;
    end

    // --- 4. OUTPUT LOGIC (Sesuai Tabel State Output Kamu) ---
    always @(*) begin
        // Default nilai 0 semua
        PS=0; PV=0; FM=0; MS=0; AL=0; SBT=0;
        state = curr_state; // Assign output debug

        case (curr_state)
            STANDBY: begin
                // 0 0 0 0 0 0 (Idle)
            end
            MONITOR: begin
                SBT = 1; // 0 0 0 0 0 1
            end
            ASSIST: begin
                PS = 1; AL = 1; // 1 0 0 0 1 0 (Pasien lemah)
            end
            SUPPORT: begin
                PS = 1; MS = 1; AL = 1; // 1 0 0 1 1 0 (Mode Mesin)
            end
            ADJ_PEEP: begin
                PV = 1; AL = 1; // 0 1 0 0 1 0 (PEEP rendah)
            end
            ADJ_FIO2: begin
                FM = 1; AL = 1; // 0 0 1 0 1 0 (Koreksi O2)
            end
            WEAN: begin
                SBT = 1; // 0 0 0 0 0 1 (Weaning/SBT)
            end
            EMERGENCY: begin
                PS=1; PV=1; FM=1; MS=1; AL=1; // 1 1 1 1 1 0 (Semua Aktif + Alarm)
            end
        endcase
    end

endmodule

Pacemaker (Verilog)/pacemaker_tb.v
// pacemaker_tb.v
`timescale 1ns/1ps

module pacemaker_tb;

    // Inputs
    reg clk, rst;
    reg VT, RR, FiO2, PEEP, EP, SpO2;

    // Outputs
    wire PS, PV, FM, MS, AL, SBT;
    wire [2:0] state;

    // Instansiasi FSM
    pacemaker_fsm UUT (
        .clk(clk), .rst(rst),
        .VT(VT), .RR(RR), .FiO2(FiO2), 
        .PEEP(PEEP), .EP(EP), .SpO2(SpO2),
        .PS(PS), .PV(PV), .FM(FM), 
        .MS(MS), .AL(AL), .SBT(SBT),
        .state(state)
    );

    // Clock Generator
    always #5 clk = ~clk;

    initial begin
        $dumpfile("pacemaker.vcd");
        $dumpvars(0, pacemaker_tb);

        // 1. Inisialisasi (STANDBY)
        clk = 0; rst = 1;
        VT=1; RR=1; FiO2=1; PEEP=1; EP=1; SpO2=1; // Semua Normal
        #10 rst = 0;

        // 2. Cek MONITOR (Semua Normal)
        #20;
        $display("[TIME %0t] State: MONITOR (001) | Out: SBT=%b", $time, SBT);

        // 3. SKENARIO: Pasien Lemah (EP = 0) -> Harusnya ke ASSIST
        $display("\n--- Tes Pasien Lemah (EP=0) ---");
        EP = 0; 
        #20;
        $display("[TIME %0t] State: %b (Harus 010/ASSIST) | PS=%b AL=%b", $time, state, PS, AL);
        EP = 1; // Balik Normal
        #20;

        // 4. SKENARIO: Oksigen Drop (SpO2 = 0) -> Harusnya ke ADJ_FIO2
        $display("\n--- Tes Oksigen Drop (SpO2=0) ---");
        SpO2 = 0;
        #20;
        $display("[TIME %0t] State: %b (Harus 101/ADJ_FIO2) | FM=%b AL=%b", $time, state, FM, AL);
        SpO2 = 1; // Balik Normal
        #20;

        // 5. SKENARIO: VT Rendah (VT = 0) -> Harusnya ke SUPPORT
        $display("\n--- Tes Volume Tidal Drop (VT=0) ---");
        VT = 0;
        #20;
        $display("[TIME %0t] State: %b (Harus 011/SUPPORT) | MS=%b AL=%b", $time, state, MS, AL);
        VT = 1; // Balik Normal
        #20;

        // 6. SKENARIO: PEEP Rendah (PEEP = 0) -> Harusnya ke ADJ_PEEP
        $display("\n--- Tes PEEP Drop (PEEP=0) ---");
        PEEP = 0;
        #20;
        $display("[TIME %0t] State: %b (Harus 100/ADJ_PEEP) | PV=%b AL=%b", $time, state, PV, AL);
        PEEP = 1;
        #20;

        // 7. SKENARIO: EMERGENCY (Banyak Sensor Gagal)
        $display("\n--- Tes EMERGENCY (VT=0, RR=0, SpO2=0) ---");
        VT=0; RR=0; SpO2=0;
        #20;
        $display("[TIME %0t] State: %b (Harus 111/EMERGENCY) | AL=%b [ALL ACTIVE]", $time, state, AL);

        // 8. Recovery
        $display("\n--- Recovery (Semua Normal) ---");
        VT=1; RR=1; SpO2=1;
        #20;
        $display("[TIME %0t] State: %b (Kembali ke 001/MONITOR)", $time, state);

        #50 $finish;
    end

endmodule

Pacemaker (Verilog)/pacemaker.vcd
$date
	Mon Dec 01 01:39:18 2025
$end
$version
	Icarus Verilog
$end
$timescale
	1ps
$end
$scope module pacemaker_tb $end
$var wire 3 ! state [2:0] $end
$var wire 1 " SBT $end
$var wire 1 # PV $end
$var wire 1 $ PS $end
$var wire 1 % MS $end
$var wire 1 & FM $end
$var wire 1 ' AL $end
$var reg 1 ( EP $end
$var reg 1 ) FiO2 $end
$var reg 1 * PEEP $end
$var reg 1 + RR $end
$var reg 1 , SpO2 $end
$var reg 1 - VT $end
$var reg 1 . clk $end
$var reg 1 / rst $end
$scope module UUT $end
$var wire 1 ( EP $end
$var wire 1 ) FiO2 $end
$var wire 1 * PEEP $end
$var wire 1 + RR $end
$var wire 1 , SpO2 $end
$var wire 1 - VT $end
$var wire 1 . clk $end
$var wire 1 / rst $end
$var wire 3 0 fail_count [2:0] $end
$var wire 1 1 all_ok $end
$var parameter 3 2 ADJ_FIO2 $end
$var parameter 3 3 ADJ_PEEP $end
$var parameter 3 4 ASSIST $end
$var parameter 3 5 EMERGENCY $end
$var parameter 3 6 MONITOR $end
$var parameter 3 7 STANDBY $end
$var parameter 3 8 SUPPORT $end
$var parameter 3 9 WEAN $end
$var reg 1 ' AL $end
$var reg 1 & FM $end
$var reg 1 % MS $end
$var reg 1 $ PS $end
$var reg 1 # PV $end
$var reg 1 " SBT $end
$var reg 3 : curr_state [2:0] $end
$var reg 3 ; next_state [2:0] $end
$var reg 3 < state [2:0] $end
$upscope $end
$upscope $end
$enddefinitions $end
$comment Show the parameter values. $end
$dumpall
b110 9
b11 8
b0 7
b1 6
b111 5
b10 4
b100 3
b101 2
$end
#0
$dumpvars
b0 <
b1 ;
b0 :
11
b0 0
1/
0.
1-
1,
1+
1*
1)
1(
0'
0&
0%
0$
0#
0"
b0 !
$end
#5000
1.
#10000
0.
0/
#15000
1"
b1 !
b1 <
b1 :
1.
#20000
0.
#25000
1.
#30000
b10 ;
0.
01
b1 0
0(
#35000
1'
1$
b10 !
b10 <
0"
b10 :
1.
#40000
0.
#45000
1.
#50000
b1 ;
0.
11
b0 0
1(
#55000
1"
b1 !
b1 <
0'
0$
b1 :
1.
#60000
0.
#65000
1.
#70000
b101 ;
0.
01
b1 0
0,
#75000
1'
1&
b101 !
b101 <
0"
b101 :
1.
#80000
0.
#85000
1.
#90000
b1 ;
0.
11
b0 0
1,
#95000
1"
b1 !
b1 <
0'
0&
b1 :
1.
#100000
0.
#105000
1.
#110000
b11 ;
0.
01
b1 0
0-
#115000
1'
1%
1$
b11 !
b11 <
0"
b11 :
1.
#120000
0.
#125000
1.
#130000
b1 ;
0.
11
b0 0
1-
#135000
1"
b1 !
b1 <
0'
0%
0$
b1 :
1.
#140000
0.
#145000
1.
#150000
b100 ;
0.
01
b1 0
0*
#155000
1'
1#
b100 !
b100 <
0"
b100 :
1.
#160000
0.
#165000
1.
#170000
b1 ;
0.
11
b0 0
1*
#175000
1"
b1 !
b1 <
0'
0#
b1 :
1.
#180000
0.
#185000
1.
#190000
b111 ;
0.
0,
0+
01
b11 0
0-
#195000
1'
1%
1&
1#
1$
b111 !
b111 <
0"
b111 :
1.
#200000
0.
#205000
1.
#210000
b1 ;
0.
11
1,
1+
b0 0
1-
#215000
1"
b1 !
b1 <
0'
0%
0&
0#
0$
b1 :
1.
